actorio_ng/__init__.py
actorio_ng/_abc.py
actorio_ng/_async_utils.py
actorio_ng/actor.py
actorio_ng/errors.py
actorio_ng/interfaces/__init__.py
actorio_ng/interfaces/identified.py
actorio_ng/messaging.py
actorio_ng/reference.py
actorio_ng-0.1.5.2.dist-info/LICENSE
actorio_ng-0.1.5.2.dist-info/METADATA
actorio_ng-0.1.5.2.dist-info/WHEEL
actorio_ng-0.1.5.2.dist-info/RECORD
