Metadata-Version: 2.3
Name: actorio-ng
Version: 0.1.5.2
Summary: A simple actor framework for asyncio
License: MIT
Author: Mark Grandi
Author-email: markgrandi@gmail.com
Requires-Python: >=3.10
Classifier: License :: OSI Approved :: MIT License
Classifier: Programming Language :: Python :: 3
Classifier: Programming Language :: Python :: 3.10
Classifier: Programming Language :: Python :: 3.11
Classifier: Programming Language :: Python :: 3.12
Classifier: Programming Language :: Python :: 3.13
Requires-Dist: pytz (>=2025.2,<2026.0)
Project-URL: Homepage, https://gitlab.com/mgrandi/actorio
Project-URL: Issues, https://gitlab.com/mgrandi/actorio/-/issues
